[
    {
        "%vlocity_namespace%__DomainObjectAPIName__c": "json",
        "%vlocity_namespace%__DomainObjectCreationOrder__c": 0,
        "%vlocity_namespace%__DomainObjectFieldAPIName__c": "OrderItem",
        "%vlocity_namespace%__FilterOperator__c": "=",
        "%vlocity_namespace%__FilterValue__c": "Id",
        "%vlocity_namespace%__InterfaceFieldAPIName__c": "OrderId",
        "%vlocity_namespace%__InterfaceObjectLookupOrder__c": 1,
        "%vlocity_namespace%__InterfaceObjectName__c": "OrderItem",
        "%vlocity_namespace%__IsDisabled__c": false,
        "%vlocity_namespace%__IsRequiredForUpsert__c": false,
        "%vlocity_namespace%__LinkCreatedIndex__c": 0,
        "%vlocity_namespace%__MapId__c": "SampleOrderItemInputCustom6769",
        "%vlocity_namespace%__UpsertKey__c": false,
        "Name": "OrderItemInput",
        "VlocityDataPackType": "SObject",
        "VlocityRecordSObjectType": "%vlocity_namespace%__DRMapItem__c"
    },
    {
        "%vlocity_namespace%__DomainObjectAPIName__c": "json",
        "%vlocity_namespace%__DomainObjectCreationOrder__c": 1,
        "%vlocity_namespace%__DomainObjectFieldAPIName__c": "Detail:Item Attr",
        "%vlocity_namespace%__InterfaceFieldAPIName__c": "OrderItem:%vlocity_namespace%__JSONAttribute__c",
        "%vlocity_namespace%__IsDisabled__c": false,
        "%vlocity_namespace%__IsRequiredForUpsert__c": false,
        "%vlocity_namespace%__LinkCreatedIndex__c": 0,
        "%vlocity_namespace%__MapId__c": "OrderItemInputCustom6533",
        "%vlocity_namespace%__UpsertKey__c": false,
        "Name": "OrderItemInput",
        "VlocityDataPackType": "SObject",
        "VlocityRecordSObjectType": "%vlocity_namespace%__DRMapItem__c"
    },
    {
        "%vlocity_namespace%__DomainObjectAPIName__c": "json",
        "%vlocity_namespace%__DomainObjectCreationOrder__c": 1,
        "%vlocity_namespace%__DomainObjectFieldAPIName__c": "Detail:OneTimeCharge",
        "%vlocity_namespace%__InterfaceFieldAPIName__c": "OrderItem:%vlocity_namespace%__OneTimeCharge__c",
        "%vlocity_namespace%__IsDisabled__c": false,
        "%vlocity_namespace%__IsRequiredForUpsert__c": false,
        "%vlocity_namespace%__LinkCreatedIndex__c": 0,
        "%vlocity_namespace%__MapId__c": "SampleOrderItemInputCustom4828",
        "%vlocity_namespace%__UpsertKey__c": false,
        "Name": "OrderItemInput",
        "VlocityDataPackType": "SObject",
        "VlocityRecordSObjectType": "%vlocity_namespace%__DRMapItem__c"
    },
    {
        "%vlocity_namespace%__DomainObjectAPIName__c": "json",
        "%vlocity_namespace%__DomainObjectCreationOrder__c": 1,
        "%vlocity_namespace%__DomainObjectFieldAPIName__c": "Detail:OneTimeManualDiscountPercent",
        "%vlocity_namespace%__InterfaceFieldAPIName__c": "OrderItem:%vlocity_namespace%__OneTimeManualDiscount__c",
        "%vlocity_namespace%__IsDisabled__c": false,
        "%vlocity_namespace%__IsRequiredForUpsert__c": false,
        "%vlocity_namespace%__LinkCreatedIndex__c": 0,
        "%vlocity_namespace%__MapId__c": "SampleOrderItemInputCustom2156",
        "%vlocity_namespace%__UpsertKey__c": false,
        "Name": "OrderItemInput",
        "VlocityDataPackType": "SObject",
        "VlocityRecordSObjectType": "%vlocity_namespace%__DRMapItem__c"
    },
    {
        "%vlocity_namespace%__DomainObjectAPIName__c": "json",
        "%vlocity_namespace%__DomainObjectCreationOrder__c": 1,
        "%vlocity_namespace%__DomainObjectFieldAPIName__c": "Detail:Product",
        "%vlocity_namespace%__InterfaceFieldAPIName__c": "OrderItem:ProductName__c",
        "%vlocity_namespace%__IsDisabled__c": false,
        "%vlocity_namespace%__IsRequiredForUpsert__c": false,
        "%vlocity_namespace%__LinkCreatedIndex__c": 0,
        "%vlocity_namespace%__MapId__c": "SampleOrderItemInputCustom1566",
        "%vlocity_namespace%__UpsertKey__c": false,
        "Name": "OrderItemInput",
        "VlocityDataPackType": "SObject",
        "VlocityRecordSObjectType": "%vlocity_namespace%__DRMapItem__c"
    },
    {
        "%vlocity_namespace%__DomainObjectAPIName__c": "json",
        "%vlocity_namespace%__DomainObjectCreationOrder__c": 1,
        "%vlocity_namespace%__DomainObjectFieldAPIName__c": "Detail:Quantity",
        "%vlocity_namespace%__InterfaceFieldAPIName__c": "OrderItem:Quantity",
        "%vlocity_namespace%__IsDisabled__c": false,
        "%vlocity_namespace%__IsRequiredForUpsert__c": false,
        "%vlocity_namespace%__LinkCreatedIndex__c": 0,
        "%vlocity_namespace%__MapId__c": "SampleOrderItemInputCustom4391",
        "%vlocity_namespace%__UpsertKey__c": false,
        "Name": "OrderItemInput",
        "VlocityDataPackType": "SObject",
        "VlocityRecordSObjectType": "%vlocity_namespace%__DRMapItem__c"
    },
    {
        "%vlocity_namespace%__DomainObjectAPIName__c": "json",
        "%vlocity_namespace%__DomainObjectCreationOrder__c": 1,
        "%vlocity_namespace%__DomainObjectFieldAPIName__c": "Detail:RecurringCharge",
        "%vlocity_namespace%__InterfaceFieldAPIName__c": "OrderItem:%vlocity_namespace%__RecurringCharge__c",
        "%vlocity_namespace%__IsDisabled__c": false,
        "%vlocity_namespace%__IsRequiredForUpsert__c": false,
        "%vlocity_namespace%__LinkCreatedIndex__c": 0,
        "%vlocity_namespace%__MapId__c": "SampleOrderItemInputCustom8532",
        "%vlocity_namespace%__UpsertKey__c": false,
        "Name": "OrderItemInput",
        "VlocityDataPackType": "SObject",
        "VlocityRecordSObjectType": "%vlocity_namespace%__DRMapItem__c"
    },
    {
        "%vlocity_namespace%__DomainObjectAPIName__c": "json",
        "%vlocity_namespace%__DomainObjectCreationOrder__c": 1,
        "%vlocity_namespace%__DomainObjectFieldAPIName__c": "Detail:RecurringManualDiscountPercent",
        "%vlocity_namespace%__InterfaceFieldAPIName__c": "OrderItem:%vlocity_namespace%__RecurringManualDiscount__c",
        "%vlocity_namespace%__IsDisabled__c": false,
        "%vlocity_namespace%__IsRequiredForUpsert__c": false,
        "%vlocity_namespace%__LinkCreatedIndex__c": 0,
        "%vlocity_namespace%__MapId__c": "SampleOrderItemInputCustom6149",
        "%vlocity_namespace%__UpsertKey__c": false,
        "Name": "OrderItemInput",
        "VlocityDataPackType": "SObject",
        "VlocityRecordSObjectType": "%vlocity_namespace%__DRMapItem__c"
    },
    {
        "%vlocity_namespace%__DomainObjectAPIName__c": "json",
        "%vlocity_namespace%__DomainObjectCreationOrder__c": 1,
        "%vlocity_namespace%__DomainObjectFieldAPIName__c": "ID",
        "%vlocity_namespace%__InterfaceFieldAPIName__c": "OrderItem:Id",
        "%vlocity_namespace%__IsDisabled__c": false,
        "%vlocity_namespace%__IsRequiredForUpsert__c": false,
        "%vlocity_namespace%__LinkCreatedIndex__c": 0,
        "%vlocity_namespace%__MapId__c": "SampleOrderItemInputCustom820",
        "%vlocity_namespace%__UpsertKey__c": false,
        "Name": "OrderItemInput",
        "VlocityDataPackType": "SObject",
        "VlocityRecordSObjectType": "%vlocity_namespace%__DRMapItem__c"
    }
]