{
    "Body": "File_TNBroadbandM-png",
    "BodyLength": 6241,
    "ContentType": "image/png",
    "Description": "",
    "IsPrivate": false,
    "Name": "TNBroadbandM.png",
    "ParentId": {
        "%vlocity_namespace%__GlobalKey__c": null,
        "VlocityDataPackType": "VlocityLookupMatchingKeyObject",
        "VlocityLookupRecordSourceKey": "VlocityRecordSourceKey:01t1I0000017EtpQAE",
        "VlocityRecordSObjectType": "Product2"
    },
    "VlocityDataPackType": "SObject",
    "VlocityRecordSObjectType": "Attachment",
    "VlocityRecordSourceKey": "Attachment/VlocityRecordSourceKey:01t1I0000017EtpQAE/TNBroadbandM.png"
}