[
    {
        "%vlocity_namespace%__ChildLineNumber__c": "1",
        "%vlocity_namespace%__ChildProductId__c": "",
        "%vlocity_namespace%__CollapseHierarchy__c": false,
        "%vlocity_namespace%__GlobalKey__c": "826a438d-6d04-b572-391e-356eecf6c2c1",
        "%vlocity_namespace%__IsOverride__c": false,
        "%vlocity_namespace%__IsRootProductChildItem__c": true,
        "%vlocity_namespace%__IsVirtualItem__c": false,
        "%vlocity_namespace%__MaxQuantity__c": 99999,
        "%vlocity_namespace%__MaximumChildItemQuantity__c": 99999,
        "%vlocity_namespace%__MinMaxDefaultQty__c": "0, 99999, 1",
        "%vlocity_namespace%__MinQuantity__c": 0,
        "%vlocity_namespace%__MinimumChildItemQuantity__c": 0,
        "%vlocity_namespace%__ParentProductId__c": {
            "%vlocity_namespace%__GlobalKey__c": "afb866ac-7127-3fa2-000b-79e5e736300e",
            "VlocityDataPackType": "VlocityMatchingKeyObject",
            "VlocityMatchingRecordSourceKey": "Product2/afb866ac-7127-3fa2-000b-79e5e736300e",
            "VlocityRecordSObjectType": "Product2"
        },
        "%vlocity_namespace%__Quantity__c": 1,
        "%vlocity_namespace%__RelationshipType__c": "Child",
        "%vlocity_namespace%__SelectionMethodImplementation__c": "",
        "%vlocity_namespace%__SeqNumber__c": 1,
        "Name": "Root PCI",
        "VlocityDataPackType": "SObject",
        "VlocityRecordSObjectType": "%vlocity_namespace%__ProductChildItem__c",
        "VlocityRecordSourceKey": "%vlocity_namespace%__ProductChildItem__c/826a438d-6d04-b572-391e-356eecf6c2c1"
    }
]