{
    "Body": "File_TN_CAE_VIP-png",
    "BodyLength": 37995,
    "ContentType": "image/png",
    "Description": "",
    "IsPrivate": false,
    "Name": "TN_CAE_VIP.png",
    "ParentId": {
        "%vlocity_namespace%__GlobalKey__c": null,
        "VlocityDataPackType": "VlocityLookupMatchingKeyObject",
        "VlocityLookupRecordSourceKey": "Product2/Generated-449623945",
        "VlocityRecordSObjectType": "Product2"
    },
    "VlocityDataPackType": "SObject",
    "VlocityRecordSObjectType": "Attachment",
    "VlocityRecordSourceKey": "Attachment/Product2/Generated-449623945/TN_CAE_VIP.png"
}